{
  "name": "Carfify - Dein intelligenter Auto-Partner",
  "short_name": "Carfify",
  "description": "KI-basierte Fahrzeugdiagnose und Verkaufsberatung",
  "start_url": "/",
  "display": "standalone",
  "orientation": "portrait",
  "theme_color": "#4fc2ee",
  "background_color": "#414959",
  "icons": [
    {
      "src": "https://via.placeholder.com/72x72/4fc2ee/ffffff?text=C",
      "sizes": "72x72",
      "type": "image/png"
    },
    {
      "src": "https://via.placeholder.com/192x192/4fc2ee/ffffff?text=C",
      "sizes": "192x192",
      "type": "image/png",
      "purpose": "any maskable"
    },
    {
      "src": "https://via.placeholder.com/512x512/4fc2ee/ffffff?text=C",
      "sizes": "512x512",
      "type": "image/png"
    }
  ],
  "categories": ["automotive", "tools", "utilities"],
  "lang": "de",
  "scope": "/",
  "prefer_related_applications": false
}